[
  {
    "id": 1,
    "date": "5/21/2023",
    "godown": "Villanova D'Albenga International Airport",
    "promise_date": "6/7/2023",
    "name": "Tommi Karolowski",
    "mobile": "5672305423",
    "address": "4 Mandrake Road",
    "voucher": "4670208012",
    "grand_total": "$11351.39",
    "paid": "$9222.20",
    "due": "$8033.34"
  },
  {
    "id": 2,
    "date": "5/1/2023",
    "godown": "Riverside Airport",
    "promise_date": "7/31/2023",
    "name": "Denna Iacavone",
    "mobile": "0718527798",
    "address": "8 Calypso Junction",
    "voucher": "8532148085",
    "grand_total": "$18550.69",
    "paid": "$5243.33",
    "due": "$6971.41"
  },
  {
    "id": 3,
    "date": "7/21/2023",
    "godown": "Kaikoura Airport",
    "promise_date": "2/9/2023",
    "name": "Harv Pursglove",
    "mobile": "1164292048",
    "address": "53 Pleasure Pass",
    "voucher": "5020381217",
    "grand_total": "$12339.68",
    "paid": "$9365.64",
    "due": "$7590.84"
  },
  {
    "id": 4,
    "date": "3/17/2023",
    "godown": "Karumba Airport",
    "promise_date": "7/2/2023",
    "name": "Clair Toseland",
    "mobile": "5685905742",
    "address": "144 Moulton Pass",
    "voucher": "5489101261",
    "grand_total": "$10866.10",
    "paid": "$8640.28",
    "due": "$7654.58"
  },
  {
    "id": 5,
    "date": "6/27/2023",
    "godown": "N'Gaoundéré Airport",
    "promise_date": "2/19/2023",
    "name": "Arvie Stobbes",
    "mobile": "6191151012",
    "address": "5918 Eggendart Street",
    "voucher": "0183472950",
    "grand_total": "$10778.16",
    "paid": "$5839.07",
    "due": "$7261.14"
  },
  {
    "id": 6,
    "date": "12/18/2023",
    "godown": "Melfi Airport",
    "promise_date": "9/19/2023",
    "name": "Maren Mepsted",
    "mobile": "9943432632",
    "address": "86 Melvin Parkway",
    "voucher": "2172335347",
    "grand_total": "$15906.63",
    "paid": "$5594.14",
    "due": "$9553.90"
  },
  {
    "id": 7,
    "date": "12/28/2023",
    "godown": "Kuria Airport",
    "promise_date": "3/31/2023",
    "name": "Wheeler Hartin",
    "mobile": "3196595013",
    "address": "702 Daystar Hill",
    "voucher": "2687342890",
    "grand_total": "$11072.76",
    "paid": "$7755.13",
    "due": "$8988.48"
  },
  {
    "id": 8,
    "date": "3/18/2023",
    "godown": "Sultan Bantilan Airport",
    "promise_date": "6/26/2023",
    "name": "Nataline Pinsent",
    "mobile": "3369475545",
    "address": "549 Vera Pass",
    "voucher": "0372371876",
    "grand_total": "$18213.58",
    "paid": "$9050.30",
    "due": "$7596.87"
  },
  {
    "id": 9,
    "date": "12/21/2023",
    "godown": "Drietabbetje Airport",
    "promise_date": "2/9/2023",
    "name": "Twyla Coulson",
    "mobile": "9352073967",
    "address": "8 Farragut Avenue",
    "voucher": "5347336374",
    "grand_total": "$18603.18",
    "paid": "$6099.55",
    "due": "$5865.84"
  },
  {
    "id": 10,
    "date": "4/27/2023",
    "godown": "Luau Airport",
    "promise_date": "1/5/2024",
    "name": "Arnoldo McCabe",
    "mobile": "0922951322",
    "address": "8531 Upham Avenue",
    "voucher": "4700508213",
    "grand_total": "$15367.88",
    "paid": "$5136.23",
    "due": "$7744.54"
  },
  {
    "id": 11,
    "date": "11/19/2023",
    "godown": "Misawa Air Base",
    "promise_date": "7/21/2023",
    "name": "Regan Daintith",
    "mobile": "3347597826",
    "address": "137 Thackeray Center",
    "voucher": "4520935539",
    "grand_total": "$14681.56",
    "paid": "$5277.50",
    "due": "$8385.31"
  },
  {
    "id": 12,
    "date": "3/9/2023",
    "godown": "M'Bigou Airport",
    "promise_date": "3/11/2023",
    "name": "Read Herculson",
    "mobile": "6489744384",
    "address": "70 Prairie Rose Way",
    "voucher": "2091070084",
    "grand_total": "$14972.49",
    "paid": "$6185.79",
    "due": "$8061.60"
  },
  {
    "id": 13,
    "date": "4/8/2023",
    "godown": "Mamfe Airport",
    "promise_date": "9/22/2023",
    "name": "Jonathan Bendson",
    "mobile": "4189644404",
    "address": "39 Northport Crossing",
    "voucher": "5321175098",
    "grand_total": "$19665.23",
    "paid": "$6370.31",
    "due": "$7669.73"
  },
  {
    "id": 14,
    "date": "7/27/2023",
    "godown": "Přerov Air Base",
    "promise_date": "8/31/2023",
    "name": "Danila Wadly",
    "mobile": "5178282000",
    "address": "6071 Katie Parkway",
    "voucher": "4211546163",
    "grand_total": "$16703.57",
    "paid": "$7558.97",
    "due": "$9389.21"
  },
  {
    "id": 15,
    "date": "11/25/2023",
    "godown": "Renmark Airport",
    "promise_date": "1/10/2024",
    "name": "Jesselyn Foale",
    "mobile": "0323682499",
    "address": "4191 Starling Park",
    "voucher": "2047350751",
    "grand_total": "$15555.57",
    "paid": "$7195.71",
    "due": "$7135.34"
  },
  {
    "id": 16,
    "date": "10/30/2023",
    "godown": "Nadym Airport",
    "promise_date": "4/6/2023",
    "name": "Jarrad Braisted",
    "mobile": "7565434310",
    "address": "0 Hansons Court",
    "voucher": "6363665329",
    "grand_total": "$18809.78",
    "paid": "$6990.87",
    "due": "$8262.57"
  },
  {
    "id": 17,
    "date": "12/25/2023",
    "godown": "Waterloo Regional Airport",
    "promise_date": "9/26/2023",
    "name": "Aloise Shimmans",
    "mobile": "3507187612",
    "address": "4074 Sauthoff Drive",
    "voucher": "5009918366",
    "grand_total": "$12835.86",
    "paid": "$9396.71",
    "due": "$9818.71"
  },
  {
    "id": 18,
    "date": "9/22/2023",
    "godown": "Vohimarina Airport",
    "promise_date": "2/1/2023",
    "name": "Pancho Bog",
    "mobile": "6654176715",
    "address": "15837 Valley Edge Pass",
    "voucher": "1393492045",
    "grand_total": "$16182.02",
    "paid": "$9247.92",
    "due": "$9939.17"
  },
  {
    "id": 19,
    "date": "12/10/2023",
    "godown": "Juist Airport",
    "promise_date": "2/19/2023",
    "name": "Wynny McVeighty",
    "mobile": "3595867742",
    "address": "8 Spohn Park",
    "voucher": "3005243915",
    "grand_total": "$14585.10",
    "paid": "$8273.76",
    "due": "$6850.87"
  },
  {
    "id": 20,
    "date": "4/11/2023",
    "godown": "Stawell Airport",
    "promise_date": "11/1/2023",
    "name": "Pansy Humbert",
    "mobile": "5267900370",
    "address": "52448 Merchant Street",
    "voucher": "9077136932",
    "grand_total": "$12003.66",
    "paid": "$8904.22",
    "due": "$7966.06"
  },
  {
    "id": 21,
    "date": "9/1/2023",
    "godown": "Huangyan Luqiao Airport",
    "promise_date": "10/29/2023",
    "name": "Bonni McGilvray",
    "mobile": "5665038512",
    "address": "23 Clemons Road",
    "voucher": "2201263612",
    "grand_total": "$19466.82",
    "paid": "$7701.68",
    "due": "$7879.78"
  },
  {
    "id": 22,
    "date": "3/15/2023",
    "godown": "Binbrook Airfield",
    "promise_date": "4/2/2023",
    "name": "Lockwood Grimestone",
    "mobile": "8004465382",
    "address": "34 Mockingbird Terrace",
    "voucher": "6363842476",
    "grand_total": "$18375.06",
    "paid": "$9252.54",
    "due": "$5594.92"
  },
  {
    "id": 23,
    "date": "7/17/2023",
    "godown": "Uriman Airport",
    "promise_date": "7/8/2023",
    "name": "Wilmar Goodrich",
    "mobile": "1684611342",
    "address": "201 Homewood Lane",
    "voucher": "3498653784",
    "grand_total": "$13328.46",
    "paid": "$9866.09",
    "due": "$9558.18"
  },
  {
    "id": 24,
    "date": "1/30/2024",
    "godown": "Patreksfjörður Airport",
    "promise_date": "7/12/2023",
    "name": "Robyn Coggin",
    "mobile": "9551264622",
    "address": "8 Walton Crossing",
    "voucher": "6304856032",
    "grand_total": "$15715.48",
    "paid": "$5289.40",
    "due": "$7304.85"
  },
  {
    "id": 25,
    "date": "2/20/2023",
    "godown": "Malevo Airport",
    "promise_date": "8/17/2023",
    "name": "Ellary Bowdon",
    "mobile": "5732618007",
    "address": "22931 Packers Avenue",
    "voucher": "3739260254",
    "grand_total": "$13812.45",
    "paid": "$8766.49",
    "due": "$9583.93"
  },
  {
    "id": 26,
    "date": "9/23/2023",
    "godown": "Wapenamanda Airport",
    "promise_date": "4/14/2023",
    "name": "Tallulah De Vaar",
    "mobile": "7451403467",
    "address": "516 Browning Junction",
    "voucher": "7463121429",
    "grand_total": "$17116.10",
    "paid": "$5214.95",
    "due": "$6158.98"
  },
  {
    "id": 27,
    "date": "6/13/2023",
    "godown": "Soummam Airport",
    "promise_date": "4/5/2023",
    "name": "Ailbert Perschke",
    "mobile": "5428770910",
    "address": "08853 Riverside Crossing",
    "voucher": "0187498083",
    "grand_total": "$13566.04",
    "paid": "$6350.68",
    "due": "$5830.11"
  },
  {
    "id": 28,
    "date": "4/24/2023",
    "godown": "Kenmore Air Harbor Inc Seaplane Base",
    "promise_date": "2/28/2023",
    "name": "Charlton Arnould",
    "mobile": "8023569007",
    "address": "4611 Buena Vista Pass",
    "voucher": "9305548865",
    "grand_total": "$14336.90",
    "paid": "$7703.14",
    "due": "$6608.54"
  },
  {
    "id": 29,
    "date": "5/28/2023",
    "godown": "General Abelardo L. Rodríguez International Airport",
    "promise_date": "3/26/2023",
    "name": "Eldredge Weekly",
    "mobile": "8312769692",
    "address": "09933 Corben Place",
    "voucher": "2273092644",
    "grand_total": "$13153.29",
    "paid": "$5750.92",
    "due": "$7516.46"
  },
  {
    "id": 30,
    "date": "4/5/2023",
    "godown": "Wagethe Airport",
    "promise_date": "12/15/2023",
    "name": "Emmet Forson",
    "mobile": "1400271681",
    "address": "480 Pennsylvania Terrace",
    "voucher": "7403524578",
    "grand_total": "$17039.14",
    "paid": "$7556.71",
    "due": "$8777.93"
  },
  {
    "id": 31,
    "date": "7/5/2023",
    "godown": "Tongren Fenghuang Airport",
    "promise_date": "1/29/2024",
    "name": "Goddard Herreran",
    "mobile": "6634590877",
    "address": "025 Farmco Parkway",
    "voucher": "2546709216",
    "grand_total": "$17254.57",
    "paid": "$8587.65",
    "due": "$9490.56"
  },
  {
    "id": 32,
    "date": "12/23/2023",
    "godown": "Lewistown Municipal Airport",
    "promise_date": "10/17/2023",
    "name": "Thomasine Markie",
    "mobile": "4268937897",
    "address": "75554 Granby Drive",
    "voucher": "9050372333",
    "grand_total": "$16524.25",
    "paid": "$7061.37",
    "due": "$8409.94"
  },
  {
    "id": 33,
    "date": "1/5/2024",
    "godown": "Saidu Sharif Airport",
    "promise_date": "1/5/2024",
    "name": "Garnette Faiers",
    "mobile": "3112830407",
    "address": "0 Buell Junction",
    "voucher": "2089485620",
    "grand_total": "$17508.45",
    "paid": "$8358.33",
    "due": "$8342.35"
  },
  {
    "id": 34,
    "date": "7/30/2023",
    "godown": "Le Puy-Loudes Airport",
    "promise_date": "2/13/2023",
    "name": "Culver Atter",
    "mobile": "0068499167",
    "address": "593 Bultman Point",
    "voucher": "2947115406",
    "grand_total": "$14860.65",
    "paid": "$7036.28",
    "due": "$8240.71"
  },
  {
    "id": 35,
    "date": "4/13/2023",
    "godown": "Gaylord Regional Airport",
    "promise_date": "8/19/2023",
    "name": "Orville Regnard",
    "mobile": "7265361555",
    "address": "19739 Coleman Center",
    "voucher": "3594968456",
    "grand_total": "$14980.35",
    "paid": "$5681.06",
    "due": "$9271.05"
  },
  {
    "id": 36,
    "date": "9/1/2023",
    "godown": "Yas Island Seaplane Base",
    "promise_date": "7/10/2023",
    "name": "Tynan Kinnane",
    "mobile": "4094065695",
    "address": "9 Moose Junction",
    "voucher": "6806361617",
    "grand_total": "$13988.66",
    "paid": "$7834.58",
    "due": "$8118.97"
  },
  {
    "id": 37,
    "date": "2/17/2023",
    "godown": "Nioro du Sahel Airport",
    "promise_date": "7/31/2023",
    "name": "Vevay Kelcey",
    "mobile": "2034528158",
    "address": "4 Pearson Circle",
    "voucher": "0171125010",
    "grand_total": "$13926.41",
    "paid": "$7569.36",
    "due": "$7991.75"
  },
  {
    "id": 38,
    "date": "12/15/2023",
    "godown": "Henri Coandă International Airport",
    "promise_date": "2/24/2023",
    "name": "Jecho Jentzsch",
    "mobile": "9845102077",
    "address": "63799 Kings Pass",
    "voucher": "7388054049",
    "grand_total": "$14900.19",
    "paid": "$8214.29",
    "due": "$9327.54"
  },
  {
    "id": 39,
    "date": "10/23/2023",
    "godown": "Phu Cat Airport",
    "promise_date": "11/2/2023",
    "name": "Bernard Chern",
    "mobile": "3927284459",
    "address": "254 Roxbury Drive",
    "voucher": "6987249741",
    "grand_total": "$15965.27",
    "paid": "$9478.47",
    "due": "$6579.57"
  },
  {
    "id": 40,
    "date": "7/11/2023",
    "godown": "Tabiteuea South Airport",
    "promise_date": "3/23/2023",
    "name": "Olivero Delahunt",
    "mobile": "3728318922",
    "address": "8 Oriole Parkway",
    "voucher": "0702539309",
    "grand_total": "$16733.61",
    "paid": "$5705.27",
    "due": "$7797.19"
  },
  {
    "id": 41,
    "date": "11/1/2023",
    "godown": "Jeongseok Airport",
    "promise_date": "3/13/2023",
    "name": "Port Stive",
    "mobile": "6832198981",
    "address": "2407 Lakeland Park",
    "voucher": "3476459322",
    "grand_total": "$11856.48",
    "paid": "$6833.28",
    "due": "$7995.02"
  },
  {
    "id": 42,
    "date": "11/29/2023",
    "godown": "Termal Airport",
    "promise_date": "3/9/2023",
    "name": "Ardene Crab",
    "mobile": "1718029969",
    "address": "2 Trailsway Street",
    "voucher": "4998390244",
    "grand_total": "$19269.36",
    "paid": "$8551.35",
    "due": "$5422.57"
  },
  {
    "id": 43,
    "date": "1/3/2024",
    "godown": "Lansdowne Airport",
    "promise_date": "2/20/2023",
    "name": "Indira Sleight",
    "mobile": "0439290155",
    "address": "5262 Marcy Court",
    "voucher": "2267338092",
    "grand_total": "$11629.45",
    "paid": "$8525.24",
    "due": "$9885.51"
  },
  {
    "id": 44,
    "date": "1/21/2024",
    "godown": "Rizhao Shanzihe Airport",
    "promise_date": "4/10/2023",
    "name": "Zorana Vella",
    "mobile": "2167736541",
    "address": "94625 Village Crossing",
    "voucher": "2443023958",
    "grand_total": "$17065.94",
    "paid": "$5558.71",
    "due": "$6504.13"
  },
  {
    "id": 45,
    "date": "10/23/2023",
    "godown": "Jubail Airport",
    "promise_date": "12/6/2023",
    "name": "Guido Bails",
    "mobile": "0905416031",
    "address": "99 Sheridan Parkway",
    "voucher": "2633006264",
    "grand_total": "$19262.41",
    "paid": "$6486.96",
    "due": "$6944.09"
  },
  {
    "id": 46,
    "date": "12/28/2023",
    "godown": "Hultsfred Airport",
    "promise_date": "10/17/2023",
    "name": "Jolee Gatward",
    "mobile": "6993597640",
    "address": "0844 Lawn Hill",
    "voucher": "7118354171",
    "grand_total": "$15226.11",
    "paid": "$8739.64",
    "due": "$9963.08"
  },
  {
    "id": 47,
    "date": "8/21/2023",
    "godown": "Elrose Airport",
    "promise_date": "10/25/2023",
    "name": "Kassi Pigden",
    "mobile": "8520323553",
    "address": "51 Anniversary Street",
    "voucher": "2976323569",
    "grand_total": "$18841.51",
    "paid": "$7125.17",
    "due": "$8830.68"
  },
  {
    "id": 48,
    "date": "1/31/2024",
    "godown": "Konya Airport",
    "promise_date": "1/19/2024",
    "name": "Bern Benner",
    "mobile": "5985949206",
    "address": "1894 Onsgard Pass",
    "voucher": "1457036436",
    "grand_total": "$18854.86",
    "paid": "$9535.17",
    "due": "$9186.17"
  },
  {
    "id": 49,
    "date": "9/6/2023",
    "godown": "Coffs Harbour Airport",
    "promise_date": "5/14/2023",
    "name": "Norman Fedorski",
    "mobile": "5006429895",
    "address": "8 Butterfield Circle",
    "voucher": "1117899748",
    "grand_total": "$15750.32",
    "paid": "$5644.08",
    "due": "$6064.53"
  },
  {
    "id": 50,
    "date": "4/24/2023",
    "godown": "Los Alamos Airport",
    "promise_date": "12/19/2023",
    "name": "Anette Bartlomiej",
    "mobile": "2019630273",
    "address": "30313 Bartillon Drive",
    "voucher": "6189911129",
    "grand_total": "$17667.10",
    "paid": "$9647.11",
    "due": "$6003.75"
  },
  {
    "id": 51,
    "date": "8/9/2023",
    "godown": "Bahawalpur Airport",
    "promise_date": "2/24/2023",
    "name": "Griz Mion",
    "mobile": "2735452832",
    "address": "125 Hintze Place",
    "voucher": "3164485530",
    "grand_total": "$14799.83",
    "paid": "$9511.38",
    "due": "$8180.43"
  },
  {
    "id": 52,
    "date": "6/26/2023",
    "godown": "Lese Airport",
    "promise_date": "7/27/2023",
    "name": "Inge Ellerman",
    "mobile": "2517573352",
    "address": "32810 Carpenter Circle",
    "voucher": "2979080705",
    "grand_total": "$13981.43",
    "paid": "$9553.29",
    "due": "$6043.17"
  },
  {
    "id": 53,
    "date": "9/13/2023",
    "godown": "Stavanger Airport Sola",
    "promise_date": "3/10/2023",
    "name": "Juana Sowte",
    "mobile": "5568331995",
    "address": "50902 Bay Circle",
    "voucher": "9817353435",
    "grand_total": "$15940.06",
    "paid": "$7089.04",
    "due": "$8180.43"
  },
  {
    "id": 54,
    "date": "12/12/2023",
    "godown": "Tabriz International Airport",
    "promise_date": "7/12/2023",
    "name": "Gram Frankton",
    "mobile": "2000649637",
    "address": "977 Pepper Wood Avenue",
    "voucher": "6722789055",
    "grand_total": "$15434.85",
    "paid": "$6169.50",
    "due": "$8649.66"
  },
  {
    "id": 55,
    "date": "5/23/2023",
    "godown": "Presidente Nicolau Lobato International Airport",
    "promise_date": "1/17/2024",
    "name": "Dylan Sutcliffe",
    "mobile": "7011712348",
    "address": "847 Independence Way",
    "voucher": "6935558476",
    "grand_total": "$16316.69",
    "paid": "$6264.20",
    "due": "$6539.71"
  },
  {
    "id": 56,
    "date": "3/18/2023",
    "godown": "Beauregard Regional Airport",
    "promise_date": "10/13/2023",
    "name": "Stace Soares",
    "mobile": "6410533489",
    "address": "3855 Russell Court",
    "voucher": "5212148278",
    "grand_total": "$13579.21",
    "paid": "$6298.34",
    "due": "$7967.63"
  },
  {
    "id": 57,
    "date": "7/29/2023",
    "godown": "Princeton Airport",
    "promise_date": "10/30/2023",
    "name": "Venus Wadlow",
    "mobile": "9392839995",
    "address": "238 Red Cloud Parkway",
    "voucher": "7341869070",
    "grand_total": "$16331.88",
    "paid": "$7648.06",
    "due": "$7101.85"
  },
  {
    "id": 58,
    "date": "2/2/2024",
    "godown": "Tôlanaro Airport",
    "promise_date": "7/22/2023",
    "name": "Tanhya Igglesden",
    "mobile": "6951583994",
    "address": "157 Briar Crest Street",
    "voucher": "6946347021",
    "grand_total": "$11033.24",
    "paid": "$9885.15",
    "due": "$9092.49"
  },
  {
    "id": 59,
    "date": "10/2/2023",
    "godown": "Bousso Airport",
    "promise_date": "9/27/2023",
    "name": "Merry Sisland",
    "mobile": "9934752085",
    "address": "12333 Browning Plaza",
    "voucher": "7747926650",
    "grand_total": "$19959.43",
    "paid": "$8674.24",
    "due": "$8165.82"
  },
  {
    "id": 60,
    "date": "11/20/2023",
    "godown": "Karawari Airstrip",
    "promise_date": "1/14/2024",
    "name": "Joeann Vader",
    "mobile": "7525586594",
    "address": "245 Ridgeview Lane",
    "voucher": "7170425963",
    "grand_total": "$18507.71",
    "paid": "$5534.34",
    "due": "$9271.58"
  },
  {
    "id": 61,
    "date": "6/9/2023",
    "godown": "Hemavan Airport",
    "promise_date": "1/18/2024",
    "name": "Delia Curtiss",
    "mobile": "6844211562",
    "address": "73814 Everett Street",
    "voucher": "9460600077",
    "grand_total": "$16735.50",
    "paid": "$8386.96",
    "due": "$9232.62"
  },
  {
    "id": 62,
    "date": "11/23/2023",
    "godown": "Pandie Pandie Airport",
    "promise_date": "4/2/2023",
    "name": "Ignatius Cusick",
    "mobile": "8864989072",
    "address": "8628 Lunder Road",
    "voucher": "1270351869",
    "grand_total": "$16289.30",
    "paid": "$9195.65",
    "due": "$9368.33"
  },
  {
    "id": 63,
    "date": "7/23/2023",
    "godown": "Sarajevo International Airport",
    "promise_date": "7/13/2023",
    "name": "Layne Wallbridge",
    "mobile": "2546136755",
    "address": "12615 Pepper Wood Center",
    "voucher": "6298973540",
    "grand_total": "$12965.12",
    "paid": "$7516.05",
    "due": "$6248.83"
  },
  {
    "id": 64,
    "date": "8/29/2023",
    "godown": "Eduardo Falla Solano Airport",
    "promise_date": "5/2/2023",
    "name": "Blanche MacShane",
    "mobile": "5821633168",
    "address": "6 6th Terrace",
    "voucher": "1279488212",
    "grand_total": "$17643.05",
    "paid": "$5737.88",
    "due": "$6940.14"
  },
  {
    "id": 65,
    "date": "12/11/2023",
    "godown": "Julia Creek Airport",
    "promise_date": "10/9/2023",
    "name": "Emelia Raymond",
    "mobile": "5490407956",
    "address": "03 Westport Road",
    "voucher": "5168717632",
    "grand_total": "$16617.04",
    "paid": "$8934.83",
    "due": "$5626.13"
  },
  {
    "id": 66,
    "date": "4/1/2023",
    "godown": "Riesa-Göhlis Airport",
    "promise_date": "6/23/2023",
    "name": "Alexandrina Cornborough",
    "mobile": "6879989942",
    "address": "3 Armistice Terrace",
    "voucher": "6261098328",
    "grand_total": "$18697.86",
    "paid": "$8235.76",
    "due": "$9524.80"
  },
  {
    "id": 67,
    "date": "8/19/2023",
    "godown": "Tabou Airport",
    "promise_date": "5/10/2023",
    "name": "Jenda Twidell",
    "mobile": "6856736177",
    "address": "6 Sheridan Center",
    "voucher": "3196417638",
    "grand_total": "$11319.89",
    "paid": "$6668.30",
    "due": "$6584.63"
  },
  {
    "id": 68,
    "date": "8/26/2023",
    "godown": "Tichitt Airport",
    "promise_date": "10/27/2023",
    "name": "Ebony Francois",
    "mobile": "3731821273",
    "address": "25 Harbort Center",
    "voucher": "3022471092",
    "grand_total": "$17038.32",
    "paid": "$5805.93",
    "due": "$7415.14"
  },
  {
    "id": 69,
    "date": "7/12/2023",
    "godown": "Mandritsara Airport",
    "promise_date": "1/11/2024",
    "name": "Dunstan Marquiss",
    "mobile": "6433263380",
    "address": "156 Kinsman Hill",
    "voucher": "8340223275",
    "grand_total": "$12465.87",
    "paid": "$9556.35",
    "due": "$9884.88"
  },
  {
    "id": 70,
    "date": "12/1/2023",
    "godown": "Council Bluffs Municipal Airport",
    "promise_date": "10/13/2023",
    "name": "Ainslie Flieg",
    "mobile": "3933864496",
    "address": "09661 Meadow Valley Way",
    "voucher": "3391796359",
    "grand_total": "$11491.62",
    "paid": "$9743.57",
    "due": "$7506.57"
  },
  {
    "id": 71,
    "date": "8/5/2023",
    "godown": "Honinabi Airport",
    "promise_date": "7/15/2023",
    "name": "Jude Saleway",
    "mobile": "3923084250",
    "address": "09 Caliangt Lane",
    "voucher": "6954342157",
    "grand_total": "$16753.44",
    "paid": "$7678.12",
    "due": "$7321.56"
  },
  {
    "id": 72,
    "date": "12/30/2023",
    "godown": "Redwood Falls Municipal Airport",
    "promise_date": "11/9/2023",
    "name": "Natividad Craister",
    "mobile": "6314241758",
    "address": "2 Meadow Valley Way",
    "voucher": "1589318889",
    "grand_total": "$15651.96",
    "paid": "$5857.55",
    "due": "$9892.40"
  },
  {
    "id": 73,
    "date": "1/6/2024",
    "godown": "Torsby Airport",
    "promise_date": "7/3/2023",
    "name": "Moise Guihen",
    "mobile": "1309697809",
    "address": "8358 Fairfield Drive",
    "voucher": "9271745647",
    "grand_total": "$13749.83",
    "paid": "$7266.52",
    "due": "$5218.45"
  },
  {
    "id": 74,
    "date": "5/25/2023",
    "godown": "Kangding Airport",
    "promise_date": "8/2/2023",
    "name": "Dugald Tander",
    "mobile": "3142681477",
    "address": "9 Sullivan Parkway",
    "voucher": "4780109396",
    "grand_total": "$18470.16",
    "paid": "$5987.66",
    "due": "$6640.18"
  },
  {
    "id": 75,
    "date": "5/20/2023",
    "godown": "Manda Airstrip",
    "promise_date": "5/10/2023",
    "name": "Bondie Hucklesby",
    "mobile": "9248353770",
    "address": "148 Basil Pass",
    "voucher": "3287059459",
    "grand_total": "$18405.64",
    "paid": "$5697.09",
    "due": "$5551.98"
  },
  {
    "id": 76,
    "date": "7/7/2023",
    "godown": "Bahrain International Airport",
    "promise_date": "8/22/2023",
    "name": "Jacklin Cristofano",
    "mobile": "6279360342",
    "address": "5 Lien Way",
    "voucher": "4286414108",
    "grand_total": "$19708.35",
    "paid": "$9227.53",
    "due": "$9051.53"
  },
  {
    "id": 77,
    "date": "7/28/2023",
    "godown": "Fazenda Tucunaré Airport",
    "promise_date": "3/12/2023",
    "name": "Jervis Mealand",
    "mobile": "5472659310",
    "address": "7 Pleasure Place",
    "voucher": "6630975316",
    "grand_total": "$11891.88",
    "paid": "$6498.20",
    "due": "$8118.58"
  },
  {
    "id": 78,
    "date": "4/27/2023",
    "godown": "Palmdale Regional/USAF Plant 42 Airport",
    "promise_date": "7/28/2023",
    "name": "Blinny Crepin",
    "mobile": "3308609150",
    "address": "52 High Crossing Road",
    "voucher": "8667180297",
    "grand_total": "$19657.43",
    "paid": "$6836.85",
    "due": "$8938.03"
  },
  {
    "id": 79,
    "date": "4/23/2023",
    "godown": "Townsville Airport",
    "promise_date": "10/21/2023",
    "name": "Lindsay Duffer",
    "mobile": "7014780956",
    "address": "68 Center Hill",
    "voucher": "3529023345",
    "grand_total": "$18706.27",
    "paid": "$5449.75",
    "due": "$5544.71"
  },
  {
    "id": 80,
    "date": "7/23/2023",
    "godown": "Portsmouth International at Pease Airport",
    "promise_date": "4/16/2023",
    "name": "Granger Itskovitz",
    "mobile": "3741654191",
    "address": "61963 Drewry Circle",
    "voucher": "2622468083",
    "grand_total": "$12811.83",
    "paid": "$6838.15",
    "due": "$7412.06"
  },
  {
    "id": 81,
    "date": "12/19/2023",
    "godown": "Lakeland-Noble F. Lee Memorial field",
    "promise_date": "2/5/2024",
    "name": "Pepito Rodda",
    "mobile": "0317886185",
    "address": "11 Corscot Circle",
    "voucher": "6455661001",
    "grand_total": "$12287.46",
    "paid": "$5336.25",
    "due": "$5272.94"
  },
  {
    "id": 82,
    "date": "11/1/2023",
    "godown": "Pattani Airport",
    "promise_date": "9/23/2023",
    "name": "Bambi Cabotto",
    "mobile": "3655149832",
    "address": "22064 Rowland Drive",
    "voucher": "7222035656",
    "grand_total": "$18248.75",
    "paid": "$8427.94",
    "due": "$5262.59"
  },
  {
    "id": 83,
    "date": "9/3/2023",
    "godown": "Brookings Airport",
    "promise_date": "10/10/2023",
    "name": "Nicolle Lasselle",
    "mobile": "7517556630",
    "address": "3 Charing Cross Street",
    "voucher": "6318530711",
    "grand_total": "$17928.02",
    "paid": "$6847.25",
    "due": "$5698.75"
  },
  {
    "id": 84,
    "date": "12/4/2023",
    "godown": "Kalay Airport",
    "promise_date": "3/19/2023",
    "name": "Fayina Ruddy",
    "mobile": "8511384197",
    "address": "5 Lien Street",
    "voucher": "5083611309",
    "grand_total": "$19879.11",
    "paid": "$7461.34",
    "due": "$5974.80"
  },
  {
    "id": 85,
    "date": "5/14/2023",
    "godown": "Inkerman Airport",
    "promise_date": "8/10/2023",
    "name": "Adrianne Brenstuhl",
    "mobile": "2037993552",
    "address": "735 Johnson Road",
    "voucher": "5182100876",
    "grand_total": "$19031.09",
    "paid": "$6771.36",
    "due": "$7446.83"
  },
  {
    "id": 86,
    "date": "9/29/2023",
    "godown": "Chaudhary Charan Singh International Airport",
    "promise_date": "5/28/2023",
    "name": "Catharine Katzmann",
    "mobile": "0866566252",
    "address": "0 Troy Court",
    "voucher": "1875062017",
    "grand_total": "$17989.07",
    "paid": "$6364.33",
    "due": "$7692.93"
  },
  {
    "id": 87,
    "date": "9/21/2023",
    "godown": "Udon Thani Airport",
    "promise_date": "9/16/2023",
    "name": "Linnet Fiddian",
    "mobile": "7609653683",
    "address": "197 Elka Junction",
    "voucher": "9962873444",
    "grand_total": "$18254.95",
    "paid": "$8208.57",
    "due": "$6727.88"
  },
  {
    "id": 88,
    "date": "7/11/2023",
    "godown": "Flagstaff Pulliam Airport",
    "promise_date": "12/28/2023",
    "name": "Alec Dinsale",
    "mobile": "6778010193",
    "address": "4791 Stoughton Street",
    "voucher": "3301487742",
    "grand_total": "$16389.85",
    "paid": "$6346.41",
    "due": "$5310.08"
  },
  {
    "id": 89,
    "date": "11/4/2023",
    "godown": "Koolburra Airport",
    "promise_date": "10/23/2023",
    "name": "Vanda Rosenau",
    "mobile": "9845006140",
    "address": "4606 Golf View Pass",
    "voucher": "1640304177",
    "grand_total": "$13363.87",
    "paid": "$5560.12",
    "due": "$6869.91"
  },
  {
    "id": 90,
    "date": "3/12/2023",
    "godown": "Ambriz Airport",
    "promise_date": "6/15/2023",
    "name": "Melody Pashen",
    "mobile": "0590123491",
    "address": "61 Dwight Junction",
    "voucher": "3458616179",
    "grand_total": "$13461.06",
    "paid": "$5787.60",
    "due": "$7185.86"
  },
  {
    "id": 91,
    "date": "11/13/2023",
    "godown": "Minatitlán/Coatzacoalcos National Airport",
    "promise_date": "5/27/2023",
    "name": "Dimitri Bodycote",
    "mobile": "6300969479",
    "address": "57112 Evergreen Park",
    "voucher": "9291608432",
    "grand_total": "$12451.43",
    "paid": "$6074.60",
    "due": "$6300.34"
  },
  {
    "id": 92,
    "date": "5/3/2023",
    "godown": "Stenkol Airport",
    "promise_date": "10/14/2023",
    "name": "Louisa Blundin",
    "mobile": "9933580779",
    "address": "4965 Heath Plaza",
    "voucher": "6163993268",
    "grand_total": "$18693.98",
    "paid": "$9953.42",
    "due": "$8415.98"
  },
  {
    "id": 93,
    "date": "11/2/2023",
    "godown": "April Point Seaplane Base",
    "promise_date": "11/29/2023",
    "name": "Clarey Brosenius",
    "mobile": "5467939467",
    "address": "8905 Butterfield Parkway",
    "voucher": "9016206590",
    "grand_total": "$13864.43",
    "paid": "$9956.47",
    "due": "$9948.85"
  },
  {
    "id": 94,
    "date": "8/5/2023",
    "godown": "Les Cayes Airport",
    "promise_date": "3/15/2023",
    "name": "Torre Bysshe",
    "mobile": "3530656062",
    "address": "5841 Jenna Way",
    "voucher": "3954021552",
    "grand_total": "$17155.99",
    "paid": "$7956.95",
    "due": "$9530.00"
  },
  {
    "id": 95,
    "date": "6/23/2023",
    "godown": "Wairoa Airport",
    "promise_date": "3/12/2023",
    "name": "Jordanna Kann",
    "mobile": "4832958348",
    "address": "9 Esker Lane",
    "voucher": "9747924404",
    "grand_total": "$12746.94",
    "paid": "$6333.49",
    "due": "$7466.53"
  },
  {
    "id": 96,
    "date": "8/23/2023",
    "godown": "Arba Minch Airport",
    "promise_date": "11/22/2023",
    "name": "Kimberly Yakuntzov",
    "mobile": "8244114541",
    "address": "84270 David Plaza",
    "voucher": "7657856440",
    "grand_total": "$14997.82",
    "paid": "$9641.85",
    "due": "$5941.89"
  },
  {
    "id": 97,
    "date": "1/10/2024",
    "godown": "Esler Regional Airport",
    "promise_date": "2/2/2024",
    "name": "Web Nicholas",
    "mobile": "4989188144",
    "address": "5 West Alley",
    "voucher": "5278670983",
    "grand_total": "$10038.03",
    "paid": "$7216.94",
    "due": "$5284.89"
  },
  {
    "id": 98,
    "date": "9/15/2023",
    "godown": "Wudinna Airport",
    "promise_date": "5/16/2023",
    "name": "Bordie Barme",
    "mobile": "3025152281",
    "address": "33 Warrior Point",
    "voucher": "6714998058",
    "grand_total": "$17028.55",
    "paid": "$7816.24",
    "due": "$9260.16"
  },
  {
    "id": 99,
    "date": "11/7/2023",
    "godown": "Camp Page Airport (A-306)",
    "promise_date": "8/31/2023",
    "name": "Chariot Hilliam",
    "mobile": "2003420614",
    "address": "76947 Grover Crossing",
    "voucher": "9594936959",
    "grand_total": "$17705.54",
    "paid": "$7255.60",
    "due": "$8159.05"
  },
  {
    "id": 100,
    "date": "9/1/2023",
    "godown": "Hartsville Regional Airport",
    "promise_date": "8/3/2023",
    "name": "Gwenny Devas",
    "mobile": "3218675103",
    "address": "37061 Ridgeview Park",
    "voucher": "7200199281",
    "grand_total": "$19554.50",
    "paid": "$9188.22",
    "due": "$5005.92"
  }
]
